idtrack/__init__.py
idtrack/__main__.py
idtrack/_api.py
idtrack/_connection_bridge.py
idtrack/_database_manager.py
idtrack/_db.py
idtrack/_external_databases.py
idtrack/_external_mappers/__init__.py
idtrack/_external_mappers/_backend_gget.py
idtrack/_external_mappers/_backend_gprofiler.py
idtrack/_external_mappers/_backend_mygene.py
idtrack/_external_mappers/_backend_pybiomart.py
idtrack/_external_mappers/_constants.py
idtrack/_external_mappers/_convert.py
idtrack/_external_mappers/_ortholog.py
idtrack/_external_mappers/_utils.py
idtrack/_graph_maker.py
idtrack/_harmonize_features.py
idtrack/_the_graph.py
idtrack/_track.py
idtrack/_track_tests.py
idtrack/_utils_hdf5.py
idtrack/_verify_organism.py
idtrack/default_config/homo_sapiens_externals_modified.yml
idtrack/default_config/homo_sapiens_externals_template.yml
idtrack/default_config/mus_musculus_externals_modified.yml
idtrack/default_config/mus_musculus_externals_template.yml
idtrack/default_config/sus_scrofa_externals_modified.yml
idtrack/default_config/sus_scrofa_externals_template.yml
idtrack/py.typed
idtrack-0.0.5.dist-info/METADATA
idtrack-0.0.5.dist-info/WHEEL
idtrack-0.0.5.dist-info/entry_points.txt
idtrack-0.0.5.dist-info/licenses/LICENSE
idtrack-0.0.5.dist-info/RECORD
