Metadata-Version: 2.4
Name: idtrack
Version: 0.0.5
Summary: Cross-Temporal and Cross-Database Biological Identifier Mapping.
License: BSD-3-Clause
License-File: LICENSE
Author: Kemal Inecik
Author-email: k.inecik@gmail.com
Requires-Python: >=3.9,<3.14
Classifier: Development Status :: 4 - Beta
Classifier: Intended Audience :: Developers
Classifier: Intended Audience :: Science/Research
Classifier: License :: OSI Approved :: BSD License
Classifier: Natural Language :: English
Classifier: Operating System :: MacOS :: MacOS X
Classifier: Operating System :: Microsoft :: Windows
Classifier: Operating System :: POSIX :: Linux
Classifier: Programming Language :: Python :: 3
Classifier: Programming Language :: Python :: 3.9
Classifier: Programming Language :: Python :: 3.10
Classifier: Programming Language :: Python :: 3.11
Classifier: Programming Language :: Python :: 3.12
Classifier: Programming Language :: Python :: 3.13
Classifier: Topic :: Scientific/Engineering :: Bio-Informatics
Provides-Extra: all-external
Provides-Extra: embeddings
Provides-Extra: external-mappers
Provides-Extra: ortholog
Requires-Dist: PyMySQL (>=0.9.3)
Requires-Dist: PySocks (>=1.7.1)
Requires-Dist: PyYAML (>=5.2,<7) ; python_version < "3.10"
Requires-Dist: PyYAML (>=6,<7) ; python_version >= "3.10"
Requires-Dist: anndata (>=0.7)
Requires-Dist: biopython (>=1.79) ; extra == "ortholog" or extra == "all-external"
Requires-Dist: gget (>=0.28) ; extra == "external-mappers" or extra == "ortholog" or extra == "all-external"
Requires-Dist: gprofiler-official (>=1.0) ; extra == "external-mappers" or extra == "all-external"
Requires-Dist: h5py (>=2.10.0)
Requires-Dist: mygene (>=3.2) ; extra == "external-mappers" or extra == "all-external"
Requires-Dist: networkx (>=2.4)
Requires-Dist: numpy (>=1.17.4)
Requires-Dist: pandas (>=0.25.3)
Requires-Dist: pybiomart (>=0.2) ; extra == "external-mappers" or extra == "all-external"
Requires-Dist: requests (>=2.32.4)
Requires-Dist: scipy (>=1.5.3)
Requires-Dist: sparse (>0.11.2)
Requires-Dist: torch (>=1.9) ; extra == "embeddings" or extra == "all-external"
Requires-Dist: tqdm (>=4.37.0)
Requires-Dist: transformers (>=4.20) ; extra == "embeddings" or extra == "all-external"
Requires-Dist: urllib3 (>=2.5.0)
Project-URL: Documentation, https://idtrack.readthedocs.io
Project-URL: Homepage, https://github.com/theislab/idtrack
Project-URL: Repository, https://github.com/theislab/idtrack
